wmul_now_playing/__init__.py
wmul_now_playing/cli.py
wmul_now_playing/display.py
wmul_now_playing/settings.py
wmul_now_playing-0.6.0.dist-info/entry_points.txt
wmul_now_playing-0.6.0.dist-info/licenses/LICENSE
wmul_now_playing-0.6.0.dist-info/WHEEL
wmul_now_playing-0.6.0.dist-info/METADATA
wmul_now_playing-0.6.0.dist-info/RECORD
