Metadata-Version: 2.4
Name: wmul_now_playing
Version: 0.6.0
Summary: 'Now Playing' display for video screens for WMUL-FM.
Author-email: Michael Stanley <stanley50@marshall.edu>
Classifier: Programming Language :: Python :: 3
Classifier: License :: OSI Approved :: MIT License
Classifier: Operating System :: OS Independent
License-File: LICENSE
Requires-Dist: wmul_logger>=0.6.0
Requires-Dist: wmul_emailer>=0.6.0
Requires-Dist: click
Requires-Dist: pygame
Requires-Dist: wmul_rivendell_tcp_client>=0.0.3
Project-URL: Bug Tracker, https://github.com/MikeTheHammer/wmul_now_playing/issues
Project-URL: Home, https://github.com/MikeTheHammer/wmul_now_playing
